nip/__init__.py
nip/constructor.py
nip/convertor.py
nip/dict.py
nip/directives.py
nip/dumper.py
nip/elements.py
nip/main.py
nip/non_seq_constructor.py
nip/stream.py
nip/tokens.py
nip/update.py
nip/utils.py
nip/parser/__init__.py
nip/parser/iter_parser.py
nip/parser/parse_func.py
nip/parser/parser.py
nip_config-0.12.2.dist-info/licenses/LICENSE
nip_config-0.12.2.dist-info/METADATA
nip_config-0.12.2.dist-info/WHEEL
nip_config-0.12.2.dist-info/top_level.txt
nip_config-0.12.2.dist-info/RECORD
