Metadata-Version: 2.4
Name: nip-config
Version: 0.12.2
Summary: Advanced configs for python
Home-page: https://github.com/spairet/nip
Author: Ilya Vasiliev
Author-email: spairet@bk.ru
Project-URL: Guide, https://github.com/spairet/nip/tree/main/doc
Project-URL: Issues, https://github.com/spairet/nip/issues
Classifier: Programming Language :: Python :: 3
Classifier: License :: OSI Approved :: MIT License
Classifier: Operating System :: OS Independent
Requires-Python: >=3.7.4
License-File: LICENSE
Requires-Dist: typeguard>=3.0.0
Dynamic: license-file
